{"cameraMode":{"drawMode":31,"name":"Sprite Mask","section":"Miscellaneous"},"sceneLighting":true,"audioPlay":false,"sceneViewState":{"m_AlwaysRefresh":true,"showFog":true,"showSkybox":true,"showFlares":true,"showImageEffects":true,"showParticleSystems":true,"showVisualEffectGraphs":true,"m_FxEnabled":false},"in2DMode":false,"pivot":{"x":4.414738655090332,"y":1.1723434925079346,"z":-0.03516904264688492},"rotation":{"x":0.0,"y":0.7071068286895752,"z":0.0,"w":0.7071068286895752},"size":3.039958953857422,"orthographic":false}